streamll/__init__.py
streamll/context.py
streamll/decorator.py
streamll/dspy_callback.py
streamll/event_consumer.py
streamll/models.py
streamll/sinks/__init__.py
streamll/sinks/rabbitmq.py
streamll/sinks/redis.py
streamll/sinks/terminal.py
streamll/streaming.py
streamll-0.1.1.dist-info/WHEEL
streamll-0.1.1.dist-info/METADATA
streamll-0.1.1.dist-info/RECORD
