Metadata-Version: 2.3
Name: streamll
Version: 0.1.1
Summary: Stream your DSPy application's inner-workings back to users in real-time
Keywords: dspy,streaming,llm,observability,ai
Author: Nick Glasson
Classifier: Development Status :: 3 - Alpha
Classifier: License :: OSI Approved :: Apache Software License
Classifier: Programming Language :: Python :: 3
Classifier: Programming Language :: Python :: 3.11
Classifier: Programming Language :: Python :: 3.12
Classifier: Programming Language :: Python :: 3.13
Requires-Dist: pydantic>=2.0
Requires-Dist: nanoid>=2.0
Requires-Dist: dspy>=2.7.0
Requires-Dist: streamll[redis,rabbitmq] ; extra == 'all'
Requires-Dist: faststream[rabbit]>=0.5.0 ; extra == 'rabbitmq'
Requires-Dist: faststream[redis]>=0.5.0 ; extra == 'redis'
Requires-Python: >=3.11
Project-URL: Homepage, https://github.com/glssn/streamll
Project-URL: Issues, https://github.com/glssn/streamll/issues
Project-URL: Repository, https://github.com/glssn/streamll
Provides-Extra: all
Provides-Extra: rabbitmq
Provides-Extra: redis
